pkai/__init__.py
pkai/atom.py
pkai/example/4k5c.pdb
pkai/example/4lzt.pdb
pkai/example/7C8J.pdb
pkai/example/example.sh
pkai/models/pKAI+_model.pt
pkai/models/pKAI_model.pt
pkai/pKAI.py
pkai/protein.py
pkai/residue.py
pkai-1.2.0.dist-info/LICENSE
pkai-1.2.0.dist-info/WHEEL
pkai-1.2.0.dist-info/METADATA
pkai-1.2.0.dist-info/RECORD
