Metadata-Version: 2.1
Name: pkai
Version: 1.2.0
Summary: A python module for flexible Poisson-Boltzmann based pKa calculations with proton tautomerism
License: MIT
Author: Pedro B.P.S. Reis
Author-email: pedro.reis@bayer.com
Requires-Python: >=3.7.0,<4.0
Classifier: Development Status :: 5 - Production/Stable
Classifier: Intended Audience :: Science/Research
Classifier: License :: OSI Approved :: MIT License
Classifier: Programming Language :: Python :: 3
Classifier: Programming Language :: Python :: 3.7
Classifier: Programming Language :: Python :: 3.8
Classifier: Programming Language :: Python :: 3.9
Classifier: Topic :: Scientific/Engineering
Requires-Dist: torch (>=1.12.0,<2.0.0)
